{
    "name": "timeout",
    "version": "1.1.0",
    "title": "jQuery Timeout",
    "author": {
        "name": "Thomas Kemmer",
        "email": "tkemmer@computer.org"
    },
    "licenses": [
        {
            "type": "MIT",
            "url": "https://github.com/tkem/jquery-timeout/blob/1.1.0/LICENSE.txt"
        }
    ],
    "dependencies": {
        "jquery": ">=1.5"
    },
    "description": "jQuery.Deferred Wrapper for setTimeout/clearTimeout.",
    "keywords": [ "timeout", "setTimeout", "delay", "deferred", "promise" ],
    "homepage": "http://tkem.github.io/jquery-timeout/",
    "bugs": "https://github.com/tkem/jquery-timeout/issues"
}
